mlbids/__init__.py
mlbids/_sfbb.py
mlbids/playeridmap.py
mlbids/data/changelog_columnmap.json
mlbids/data/changelog_columns.json
mlbids/data/playeridmap_columnmap.json
mlbids/data/playeridmap_columns.json
mlbids/tests/__init__.py
MLBPlayerIDs-0.1.0.dist-info/LICENSE
MLBPlayerIDs-0.1.0.dist-info/METADATA
MLBPlayerIDs-0.1.0.dist-info/WHEEL
MLBPlayerIDs-0.1.0.dist-info/top_level.txt
MLBPlayerIDs-0.1.0.dist-info/RECORD
