Metadata-Version: 2.1
Name: MLBPlayerIDs
Version: 0.1.0
Summary: A package for scraping IDs for MLB players
Home-page: https://github.com/JLpython-py/MLBPlayerIDs
Author: Jacob Lee
Author-email: JLpython@outlook.com
License: UNKNOWN
Platform: UNKNOWN
Classifier: Development Status :: 3 - Alpha
Classifier: Intended Audience :: Developers
Classifier: License :: OSI Approved :: MIT License
Classifier: Operating System :: OS Independent
Classifier: Programming Language :: Python :: 3
Classifier: Programming Language :: Python :: 3.8
Classifier: Programming Language :: Python :: 3.9
Classifier: Programming Language :: Python :: 3.10
Requires-Python: >=3.8
License-File: LICENSE
